README.md
setup.py
fruition/__init__.py
fruition/__main__.py
fruition/py.typed
fruition/setup.py
fruition.egg-info/PKG-INFO
fruition.egg-info/SOURCES.txt
fruition.egg-info/dependency_links.txt
fruition.egg-info/entry_points.txt
fruition.egg-info/requires.txt
fruition.egg-info/top_level.txt
fruition/api/__init__.py
fruition/api/base.py
fruition/api/configuration.py
fruition/api/exceptions.py
fruition/api/client/__init__.py
fruition/api/client/base.py
fruition/api/client/googlerpc.py
fruition/api/client/wrapper.py
fruition/api/client/apachethrift/__init__.py
fruition/api/client/apachethrift/wrapper.py
fruition/api/client/file/__init__.py
fruition/api/client/file/base.py
fruition/api/client/file/ftp.py
fruition/api/client/file/hdfs.py
fruition/api/client/file/local.py
fruition/api/client/file/sftp.py
fruition/api/client/webservice/__init__.py
fruition/api/client/webservice/apachethrift.py
fruition/api/client/webservice/base.py
fruition/api/client/webservice/jsonapi.py
fruition/api/client/webservice/soap.py
fruition/api/client/webservice/wrapper.py
fruition/api/client/webservice/rpc/__init__.py
fruition/api/client/webservice/rpc/base.py
fruition/api/client/webservice/rpc/jsonrpc.py
fruition/api/client/webservice/rpc/xmlrpc.py
fruition/api/helpers/__init__.py
fruition/api/helpers/apachethrift.py
fruition/api/helpers/authentication.py
fruition/api/helpers/googlerpc.py
fruition/api/helpers/store.py
fruition/api/helpers/wrappers.py
fruition/api/meta/__init__.py
fruition/api/meta/base.py
fruition/api/meta/helpers.py
fruition/api/middleware/__init__.py
fruition/api/middleware/base.py
fruition/api/middleware/screening.py
fruition/api/middleware/apachethrift/__init__.py
fruition/api/middleware/apachethrift/base.py
fruition/api/middleware/apachethrift/screening.py
fruition/api/middleware/database/__init__.py
fruition/api/middleware/database/orm.py
fruition/api/middleware/file/__init__.py
fruition/api/middleware/file/temp.py
fruition/api/middleware/googlerpc/__init__.py
fruition/api/middleware/googlerpc/authentication.py
fruition/api/middleware/googlerpc/base.py
fruition/api/middleware/googlerpc/metadata.py
fruition/api/middleware/webservice/__init__.py
