Metadata-Version: 2.1
Name: fruition
Version: 0.9.1
Summary: A framework for developing webapps quickly and easily using Python, SQLAlchemy, and Jinja2. Supports numerous protocols, databases, and web drivers.
Home-page: https://github.com/painebenjamin/fruition
Author: Benjamin Paine
Author-email: painebenjamin@gmail.com
License: gpl-3.0
Classifier: Development Status :: 4 - Beta
Classifier: Intended Audience :: Developers
Classifier: License :: OSI Approved :: GNU General Public License v3 (GPLv3)
Classifier: Operating System :: OS Independent
Classifier: Programming Language :: Python :: 3
Classifier: Programming Language :: Python :: 3.9
Classifier: Programming Language :: Python :: 3.10
Classifier: Programming Language :: Python :: 3.11
Classifier: Programming Language :: Python :: 3.12
Requires-Dist: bcrypt<4.1,>=4.0
Requires-Dist: chardet<5.2,>=5.0
Requires-Dist: click<9.0,>=8.0
Requires-Dist: configparser<5.4,>=5.2
Requires-Dist: jinja2<3.2,>=3.0
Requires-Dist: mimeparse>=0.1
Requires-Dist: pandas<3.0,>=2.0
Requires-Dist: pycryptodome<4.0,>=3.17
Requires-Dist: pyopenssl<24.0,>=23.1
Requires-Dist: pyyaml<7.0,>=6.0
Requires-Dist: requests<3.0,>=2.12
Requires-Dist: requests-oauthlib<2.0,>=1.3
Requires-Dist: semantic-version<3.0,>=2.10
Requires-Dist: sqlalchemy<2.0,>=1.1
Requires-Dist: sshpubkeys<4.0,>=3.3
Requires-Dist: termcolor<3.0,>=1.0
Requires-Dist: webob<2.0,>=1.8
Requires-Dist: zeep<5.0,>=4.2
Requires-Dist: paramiko<4.0,>=3.1
Requires-Dist: pillow<11.0,>=9.0
Provides-Extra: mysql
Requires-Dist: mysqlclient<2.2,>=2.1; extra == "mysql"
Provides-Extra: postgresql
Requires-Dist: psycopg2-binary<3.0,>=2.9; extra == "postgresql"
Provides-Extra: mssql
Requires-Dist: pyodbc<6.0,>=5.0; extra == "mssql"
Requires-Dist: sqlalchemy-pyodbc-mssql>=0.1; extra == "mssql"
Provides-Extra: thrift
Requires-Dist: thrift<1.0,>=0.16; extra == "thrift"
Provides-Extra: grpc
Requires-Dist: grpcio; extra == "grpc"
Requires-Dist: grpcio-tools; extra == "grpc"
Provides-Extra: browser
Requires-Dist: selenium<5.0,>=4.8; extra == "browser"
Provides-Extra: imaging
Requires-Dist: pdf2image<2.0,>=1.16; extra == "imaging"
Requires-Dist: pillow<11.0,>=10.0; extra == "imaging"
Requires-Dist: psd-tools<2.0,>=1.9; extra == "imaging"
Provides-Extra: cherrypy
Requires-Dist: cherrypy<19.0,>=18.8; extra == "cherrypy"
Provides-Extra: gunicorn
Requires-Dist: gunicorn<21.0,>=20.0; extra == "gunicorn"
Provides-Extra: werkzeug
Requires-Dist: werkzeug<3.0,>=2.2; extra == "werkzeug"
Provides-Extra: excel
Requires-Dist: openpyxl<4.0,>=3.1; extra == "excel"
Requires-Dist: xlrd<3.0,>=2.0; extra == "excel"
Provides-Extra: aws
Requires-Dist: boto3<2.0,>=1.26; extra == "aws"
Provides-Extra: ftp
Requires-Dist: pyftpdlib<2.0,>=1.5; extra == "ftp"
Provides-Extra: xml
Requires-Dist: lxml<5.0,>=4.9; extra == "xml"
Provides-Extra: build
Requires-Dist: sphinx<6.3,>=6.2; extra == "build"
Requires-Dist: sphinx-rtd-theme<1.3,>=1.2; extra == "build"
Requires-Dist: types-PyYAML<6.1,>=6.0.12; extra == "build"
Requires-Dist: types-chardet<6.0,>=5.0.4; extra == "build"
Requires-Dist: types-requests<3.0,>=2.29; extra == "build"
Requires-Dist: types-termcolor<1.2,>=1.1.6; extra == "build"
Requires-Dist: types-pytz>=2023.3; extra == "build"
Requires-Dist: types-python-dateutil<3.0,>=2.8.19; extra == "build"
Requires-Dist: types-protobuf<5.0,>=4.22; extra == "build"
Requires-Dist: types-pillow<11.0,>=10.0; extra == "build"
Requires-Dist: types-paramiko<4.0,>=3.0; extra == "build"
Requires-Dist: types-oauthlib<4.0,>=3.2; extra == "build"
Requires-Dist: types-openpyxl==3.0.0; extra == "build"
Requires-Dist: types-urllib3<1.27; extra == "build"
Requires-Dist: importchecker<3.0,>=2.0; extra == "build"
Requires-Dist: black<24.0,>=23.3; extra == "build"
Requires-Dist: twine<5.0,>=4.0; extra == "build"
Requires-Dist: mypy<1.3,>=1.2; extra == "build"
Provides-Extra: all
Requires-Dist: mysqlclient<2.2,>=2.1; extra == "all"
Requires-Dist: psycopg2-binary<3.0,>=2.9; extra == "all"
Requires-Dist: pyodbc<6.0,>=5.0; extra == "all"
Requires-Dist: sqlalchemy-pyodbc-mssql>=0.1; extra == "all"
Requires-Dist: thrift<1.0,>=0.16; extra == "all"
Requires-Dist: grpcio; extra == "all"
Requires-Dist: grpcio-tools; extra == "all"
Requires-Dist: selenium<5.0,>=4.8; extra == "all"
Requires-Dist: pdf2image<2.0,>=1.16; extra == "all"
Requires-Dist: pillow<11.0,>=10.0; extra == "all"
Requires-Dist: psd-tools<2.0,>=1.9; extra == "all"
Requires-Dist: cherrypy<19.0,>=18.8; extra == "all"
Requires-Dist: gunicorn<21.0,>=20.0; extra == "all"
Requires-Dist: werkzeug<3.0,>=2.2; extra == "all"
Requires-Dist: openpyxl<4.0,>=3.1; extra == "all"
Requires-Dist: xlrd<3.0,>=2.0; extra == "all"
Requires-Dist: boto3<2.0,>=1.26; extra == "all"
Requires-Dist: pyftpdlib<2.0,>=1.5; extra == "all"
Requires-Dist: lxml<5.0,>=4.9; extra == "all"
Requires-Dist: sphinx<6.3,>=6.2; extra == "all"
Requires-Dist: sphinx-rtd-theme<1.3,>=1.2; extra == "all"
Requires-Dist: types-PyYAML<6.1,>=6.0.12; extra == "all"
Requires-Dist: types-chardet<6.0,>=5.0.4; extra == "all"
Requires-Dist: types-requests<3.0,>=2.29; extra == "all"
Requires-Dist: types-termcolor<1.2,>=1.1.6; extra == "all"
Requires-Dist: types-pytz>=2023.3; extra == "all"
Requires-Dist: types-python-dateutil<3.0,>=2.8.19; extra == "all"
Requires-Dist: types-protobuf<5.0,>=4.22; extra == "all"
Requires-Dist: types-pillow<11.0,>=10.0; extra == "all"
Requires-Dist: types-paramiko<4.0,>=3.0; extra == "all"
Requires-Dist: types-oauthlib<4.0,>=3.2; extra == "all"
Requires-Dist: types-openpyxl==3.0.0; extra == "all"
Requires-Dist: types-urllib3<1.27; extra == "all"
Requires-Dist: importchecker<3.0,>=2.0; extra == "all"
Requires-Dist: black<24.0,>=23.3; extra == "all"
Requires-Dist: twine<5.0,>=4.0; extra == "all"
Requires-Dist: mypy<1.3,>=1.2; extra == "all"
